lexwolf/__init__.py
lexwolf/adaptativeminmax.py
lexwolf/bitBoard.py
lexwolf/core.py
lexwolf/dEvalTest.py
lexwolf/genetic.py
lexwolf/interfpsql.py
lexwolf/minmax.py
lexwolf/openings_fen7.csv
lexwolf/structEl.py
lexwolf/tests.py
lexwolf/weights.py
lexwolf-0.2.3.dist-info/LICENSE
lexwolf-0.2.3.dist-info/METADATA
lexwolf-0.2.3.dist-info/WHEEL
lexwolf-0.2.3.dist-info/top_level.txt
lexwolf-0.2.3.dist-info/RECORD
